odoo/addons/purchase_stock_picking_invoice_link/README.rst
odoo/addons/purchase_stock_picking_invoice_link/__init__.py
odoo/addons/purchase_stock_picking_invoice_link/__manifest__.py
odoo/addons/purchase_stock_picking_invoice_link/i18n/es.po
odoo/addons/purchase_stock_picking_invoice_link/i18n/fr.po
odoo/addons/purchase_stock_picking_invoice_link/i18n/hr.po
odoo/addons/purchase_stock_picking_invoice_link/i18n/it.po
odoo/addons/purchase_stock_picking_invoice_link/i18n/pt.po
odoo/addons/purchase_stock_picking_invoice_link/i18n/pt_BR.po
odoo/addons/purchase_stock_picking_invoice_link/i18n/purchase_stock_picking_invoice_link.pot
odoo/addons/purchase_stock_picking_invoice_link/models/__init__.py
odoo/addons/purchase_stock_picking_invoice_link/models/purchase_order.py
odoo/addons/purchase_stock_picking_invoice_link/models/stock_move.py
odoo/addons/purchase_stock_picking_invoice_link/readme/CONTRIBUTORS.md
odoo/addons/purchase_stock_picking_invoice_link/readme/DESCRIPTION.md
odoo/addons/purchase_stock_picking_invoice_link/readme/USAGE.md
odoo/addons/purchase_stock_picking_invoice_link/static/description/icon.png
odoo/addons/purchase_stock_picking_invoice_link/static/description/index.html
odoo/addons/purchase_stock_picking_invoice_link/tests/__init__.py
odoo/addons/purchase_stock_picking_invoice_link/tests/test_purchase_stock_picking_invoice_link.py
odoo_addon_purchase_stock_picking_invoice_link-18.0.2.0.0.1.dist-info/METADATA
odoo_addon_purchase_stock_picking_invoice_link-18.0.2.0.0.1.dist-info/WHEEL
odoo_addon_purchase_stock_picking_invoice_link-18.0.2.0.0.1.dist-info/top_level.txt
odoo_addon_purchase_stock_picking_invoice_link-18.0.2.0.0.1.dist-info/RECORD
