Metadata-Version: 2.1
Name: odoo-addon-purchase_stock_picking_invoice_link
Version: 18.0.2.0.0.1
Requires-Python: >=3.10
Requires-Dist: odoo-addon-stock_picking_invoice_link==18.0.*
Requires-Dist: odoo==18.0.*
Summary: Adds link between purchases, pickings and invoices
Home-page: https://github.com/OCA/stock-logistics-workflow
License: AGPL-3
Author: Tecnativa, Odoo Community Association (OCA)
Author-email: support@odoo-community.org
Classifier: Programming Language :: Python
Classifier: Framework :: Odoo
Classifier: Framework :: Odoo :: 18.0
Classifier: License :: OSI Approved :: GNU Affero General Public License v3
